Workbook

Sheet Dashboard
A1: AI Software Engineer OS — Dashboard
A2: Single source of truth for your 10-week journey to FAANG-level AI engineering
A4: Overall Progress | C4: Current Week | E4: Hours Logged | G4: Hours Target
A5: =IFERROR(COUNTIF('Daily Tasks'!K:K,"Complete")/70,0) | C5: =MIN(10, INT((COUNTIF('Daily Tasks'!K:K,"Complete"))/7)+1) | E5: =SUM('Daily Tasks'!J:J) | G5: 500
A9: Tasks Complete | C9: Tasks Total | E9: Streak (days) | G9: Interview Qs Solved
A10: =COUNTIF('Daily Tasks'!K:K,"Complete") | C10: 70 | E10: 0 | G10: =COUNTIFS('Interview Prep'!E:E,"Complete")
A15: Weekly Progress Summary
A16: Week | B16: Phase | C16: Status | D16: Completion % | E16: Hours Logged | F16: Hours Target | G16: Tasks Complete | H16: Tasks Total
A17: 1 | B17: ='Weekly Goals'!B5 | C17: ='Weekly Goals'!J5 | D17: ='Weekly Goals'!I5 | E17: ='Weekly Goals'!H5 | F17: ='Weekly Goals'!G5 | G17: =COUNTIFS('Daily Tasks'!B:B,1,'Daily Tasks'!K:K,"Complete") | H17: =COUNTIF('Daily Tasks'!B:B,1)
A18: 2 | B18: ='Weekly Goals'!B6 | C18: ='Weekly Goals'!J6 | D18: ='Weekly Goals'!I6 | E18: ='Weekly Goals'!H6 | F18: ='Weekly Goals'!G6 | G18: =COUNTIFS('Daily Tasks'!B:B,2,'Daily Tasks'!K:K,"Complete") | H18: =COUNTIF('Daily Tasks'!B:B,2)
A19: 3 | B19: ='Weekly Goals'!B7 | C19: ='Weekly Goals'!J7 | D19: ='Weekly Goals'!I7 | E19: ='Weekly Goals'!H7 | F19: ='Weekly Goals'!G7 | G19: =COUNTIFS('Daily Tasks'!B:B,3,'Daily Tasks'!K:K,"Complete") | H19: =COUNTIF('Daily Tasks'!B:B,3)
A20: 4 | B20: ='Weekly Goals'!B8 | C20: ='Weekly Goals'!J8 | D20: ='Weekly Goals'!I8 | E20: ='Weekly Goals'!H8 | F20: ='Weekly Goals'!G8 | G20: =COUNTIFS('Daily Tasks'!B:B,4,'Daily Tasks'!K:K,"Complete") | H20: =COUNTIF('Daily Tasks'!B:B,4)
A21: 5 | B21: ='Weekly Goals'!B9 | C21: ='Weekly Goals'!J9 | D21: ='Weekly Goals'!I9 | E21: ='Weekly Goals'!H9 | F21: ='Weekly Goals'!G9 | G21: =COUNTIFS('Daily Tasks'!B:B,5,'Daily Tasks'!K:K,"Complete") | H21: =COUNTIF('Daily Tasks'!B:B,5)
A22: 6 | B22: ='Weekly Goals'!B10 | C22: ='Weekly Goals'!J10 | D22: ='Weekly Goals'!I10 | E22: ='Weekly Goals'!H10 | F22: ='Weekly Goals'!G10 | G22: =COUNTIFS('Daily Tasks'!B:B,6,'Daily Tasks'!K:K,"Complete") | H22: =COUNTIF('Daily Tasks'!B:B,6)
A23: 7 | B23: ='Weekly Goals'!B11 | C23: ='Weekly Goals'!J11 | D23: ='Weekly Goals'!I11 | E23: ='Weekly Goals'!H11 | F23: ='Weekly Goals'!G11 | G23: =COUNTIFS('Daily Tasks'!B:B,7,'Daily Tasks'!K:K,"Complete") | H23: =COUNTIF('Daily Tasks'!B:B,7)
A24: 8 | B24: ='Weekly Goals'!B12 | C24: ='Weekly Goals'!J12 | D24: ='Weekly Goals'!I12 | E24: ='Weekly Goals'!H12 | F24: ='Weekly Goals'!G12 | G24: =COUNTIFS('Daily Tasks'!B:B,8,'Daily Tasks'!K:K,"Complete") | H24: =COUNTIF('Daily Tasks'!B:B,8)
A25: 9 | B25: ='Weekly Goals'!B13 | C25: ='Weekly Goals'!J13 | D25: ='Weekly Goals'!I13 | E25: ='Weekly Goals'!H13 | F25: ='Weekly Goals'!G13 | G25: =COUNTIFS('Daily Tasks'!B:B,9,'Daily Tasks'!K:K,"Complete") | H25: =COUNTIF('Daily Tasks'!B:B,9)
A26: 10 | B26: ='Weekly Goals'!B14 | C26: ='Weekly Goals'!J14 | D26: ='Weekly Goals'!I14 | E26: ='Weekly Goals'!H14 | F26: ='Weekly Goals'!G14 | G26: =COUNTIFS('Daily Tasks'!B:B,10,'Daily Tasks'!K:K,"Complete") | H26: =COUNTIF('Daily Tasks'!B:B,10)
A28: Readiness Scores (0-100, self-assess weekly)
A29: Domain | B29: Score | C29: Level | D29: Notes
A30: Python | B30: 0 | C30: =IF(B30>=80,"Strong",IF(B30>=50,"Growing",IF(B30>=20,"Learning","Beginner")))
A31: SQL | B31: 0 | C31: =IF(B31>=80,"Strong",IF(B31>=50,"Growing",IF(B31>=20,"Learning","Beginner")))
A32: DSA | B32: 0 | C32: =IF(B32>=80,"Strong",IF(B32>=50,"Growing",IF(B32>=20,"Learning","Beginner")))
A33: System Design | B33: 0 | C33: =IF(B33>=80,"Strong",IF(B33>=50,"Growing",IF(B33>=20,"Learning","Beginner")))
A34: Backend / FastAPI | B34: 0 | C34: =IF(B34>=80,"Strong",IF(B34>=50,"Growing",IF(B34>=20,"Learning","Beginner")))
A35: Docker / Cloud | B35: 0 | C35: =IF(B35>=80,"Strong",IF(B35>=50,"Growing",IF(B35>=20,"Learning","Beginner")))
A36: ML Foundations | B36: 0 | C36: =IF(B36>=80,"Strong",IF(B36>=50,"Growing",IF(B36>=20,"Learning","Beginner")))
A37: LLM | B37: 0 | C37: =IF(B37>=80,"Strong",IF(B37>=50,"Growing",IF(B37>=20,"Learning","Beginner")))
A38: RAG | B38: 0 | C38: =IF(B38>=80,"Strong",IF(B38>=50,"Growing",IF(B38>=20,"Learning","Beginner")))
A39: AI Agents | B39: 0 | C39: =IF(B39>=80,"Strong",IF(B39>=50,"Growing",IF(B39>=20,"Learning","Beginner")))

Sheet Weekly Goals
A1: Weekly Goals
A2: Your 10-week phased curriculum — themes, objectives & deliverables
A4: Week # | B4: Phase Name | C4: Theme | D4: Primary Objectives | E4: Key Topics | F4: Deliverable / Milestone | G4: Target Hours | H4: Hours Logged | I4: Completion % | J4: Status | K4: Notes
A5: 1 | B5: Foundations | C5: Setup & Python Mastery | D5: Set up a professional dev environment • Master Git/GitHub workflows • Refresh Python deeply with type hints • Get comfortable on Linux CLI • Learn pytest basics | E5: VS Code, Git, GitHub, Linux CLI, Python 3.11, type hints, virtualenv, pip, ruff, black, mypy, pytest | F5: Working CLI Task Manager + clean dev environment | G5: 45 | H5: =SUMIF('Daily Tasks'!B:B,1,'Daily Tasks'!J:J) | I5: =IFERROR(COUNTIFS('Daily Tasks'!B:B,1,'Daily Tasks'!K:K,"Complete")/COUNTIF('Daily Tasks'!B:B,1),0) | J5: Not Started
A6: 2 | B6: CS Fundamentals | C6: Core Computer Science | D6: Understand OS internals • Grasp networking from sockets to HTTP • Learn relational DB theory • Build intuition for indexes & transactions • Create 50 flashcards | E6: Processes, threads, memory, scheduling, TCP/IP, HTTP/2, DNS, sockets, SQL, normalization, indexes, transactions, ACID | F6: CS Fundamentals notes + 50 spaced-repetition flashcards | G6: 50 | H6: =SUMIF('Daily Tasks'!B:B,2,'Daily Tasks'!J:J) | I6: =IFERROR(COUNTIFS('Daily Tasks'!B:B,2,'Daily Tasks'!K:K,"Complete")/COUNTIF('Daily Tasks'!B:B,2),0) | J6: Not Started
A7: 3 | B7: Software Engineering | C7: Clean Code & Testing | D7: Internalize SOLID • Apply core design patterns • Write maintainable code • Master unit + integration testing • Design proper REST APIs | E7: SOLID, GoF patterns, clean code, pytest, mocking, TDD, REST design, API versioning, OpenAPI | F7: Refactored TODO API with 90%+ test coverage | G7: 50 | H7: =SUMIF('Daily Tasks'!B:B,3,'Daily Tasks'!J:J) | I7: =IFERROR(COUNTIFS('Daily Tasks'!B:B,3,'Daily Tasks'!K:K,"Complete")/COUNTIF('Daily Tasks'!B:B,3),0) | J7: Not Started
A8: 4 | B8: Backend Mastery | C8: FastAPI & Postgres | D8: Build production FastAPI services • Model with SQLAlchemy 2.0 • Validate with Pydantic v2 • Implement JWT auth • Add background tasks | E8: FastAPI, SQLAlchemy 2.0, Alembic, Pydantic v2, JWT, OAuth2, middleware, dependency injection, background tasks | F8: Production REST API with auth, migrations & docs | G8: 55 | H8: =SUMIF('Daily Tasks'!B:B,4,'Daily Tasks'!J:J) | I8: =IFERROR(COUNTIFS('Daily Tasks'!B:B,4,'Daily Tasks'!K:K,"Complete")/COUNTIF('Daily Tasks'!B:B,4),0) | J8: Not Started
A9: 5 | B9: DevOps & Cloud | C9: Docker, AWS, CI/CD | D9: Containerize multi-service apps • Deploy to AWS • Build CI/CD pipelines • Configure Nginx reverse proxy • Manage secrets properly | E9: Docker, docker-compose, multi-stage builds, AWS EC2, S3, RDS, Lambda, GitHub Actions, Nginx, env vars | F9: Dockerized app deployed live to AWS via CI/CD | G9: 50 | H9: =SUMIF('Daily Tasks'!B:B,5,'Daily Tasks'!J:J) | I9: =IFERROR(COUNTIFS('Daily Tasks'!B:B,5,'Daily Tasks'!K:K,"Complete")/COUNTIF('Daily Tasks'!B:B,5),0) | J9: Not Started
A10: 6 | B10: ML & LLM Foundations | C10: From Numpy to Transformers | D10: Refresh NumPy/Pandas • Train classical ML models • Build neural nets from scratch • Understand Transformer architecture • Use HuggingFace pipelines | E10: NumPy, Pandas, scikit-learn, PyTorch basics, MLPs, backprop, attention, Transformer blocks, HuggingFace, tokenization | F10: Sentiment Analysis API powered by HuggingFace | G10: 55 | H10: =SUMIF('Daily Tasks'!B:B,6,'Daily Tasks'!J:J) | I10: =IFERROR(COUNTIFS('Daily Tasks'!B:B,6,'Daily Tasks'!K:K,"Complete")/COUNTIF('Daily Tasks'!B:B,6),0) | J10: Not Started
A11: 7 | B11: RAG & Vector DBs | C11: Retrieval-Augmented Generation | D11: Master embeddings + chunking • Operate vector DBs • Implement hybrid search • Engineer prompts systematically • Evaluate RAG quality | E11: Embeddings, chunking strategies, Pinecone, Chroma, Qdrant, pgvector, hybrid search, prompt engineering, RAGAS | F11: Documentation Chatbot with production-grade RAG | G11: 55 | H11: =SUMIF('Daily Tasks'!B:B,7,'Daily Tasks'!J:J) | I11: =IFERROR(COUNTIFS('Daily Tasks'!B:B,7,'Daily Tasks'!K:K,"Complete")/COUNTIF('Daily Tasks'!B:B,7),0) | J11: Not Started
A12: 8 | B12: AI Agents | C12: LangGraph & Multi-Agent | D12: Build agents with LangChain • Orchestrate with LangGraph • Implement tool use • Understand MCP protocol • Compose multi-agent systems | E12: LangChain, LangGraph, ReAct, Plan-and-Execute, tool calling, MCP, agent memory, multi-agent orchestration | F12: Multi-Agent Research Assistant w/ web + code tools | G12: 50 | H12: =SUMIF('Daily Tasks'!B:B,8,'Daily Tasks'!J:J) | I12: =IFERROR(COUNTIFS('Daily Tasks'!B:B,8,'Daily Tasks'!K:K,"Complete")/COUNTIF('Daily Tasks'!B:B,8),0) | J12: Not Started
A13: 9 | B13: System Design & Production AI | C13: Scale & Serve | D13: Design scalable systems • Apply caching + queues • Serve LLMs in production • Add observability • Optimize cost & latency | E13: Scalability patterns, caching (Redis), queues (Kafka, SQS), microservices, vLLM, TGI, Prometheus, Grafana, cost ops | F13: LLM Gateway: rate-limited, cached, observable | G13: 50 | H13: =SUMIF('Daily Tasks'!B:B,9,'Daily Tasks'!J:J) | I13: =IFERROR(COUNTIFS('Daily Tasks'!B:B,9,'Daily Tasks'!K:K,"Complete")/COUNTIF('Daily Tasks'!B:B,9),0) | J13: Not Started
A14: 10 | B14: Capstone & Interviews | C14: Ship & Prepare | D14: Build end-to-end AI SaaS capstone • Polish portfolio site • Do 5 mock interviews • Refine resume • Prep behavioral stories | E14: Full-stack AI SaaS, Next.js, FastAPI, pgvector, agents, Stripe-mock, portfolio site, resume, STAR stories | F14: Capstone live + portfolio + 5 mock interviews done | G14: 40 | H14: =SUMIF('Daily Tasks'!B:B,10,'Daily Tasks'!J:J) | I14: =IFERROR(COUNTIFS('Daily Tasks'!B:B,10,'Daily Tasks'!K:K,"Complete")/COUNTIF('Daily Tasks'!B:B,10),0) | J14: Not Started

Sheet Daily Tasks
A1: Daily Tasks
A2: Your 70-day battle plan — one row per day
A4: Day # | B4: Week # | C4: Date | D4: Phase | E4: Topic | F4: Task Description | G4: Task Type | H4: Resource / Reference | I4: Est. Hours | J4: Actual Hours | K4: Status | L4: Notes
A5: 1 | B5: 1 | D5: Foundations | E5: Dev Environment | F5: Install VS Code, Python 3.11 via pyenv; configure ruff, black, mypy; create dotfiles repo on GitHub | G5: Code | H5: Real Python: Setting up Python | I5: 4 | J5: 0 | K5: Not Started
A6: 2 | B6: 1 | D6: Foundations | E6: Git Basics | F6: Read Pro Git chapters 1-3; practice init/add/commit/branch/merge in scratch repo | G6: Reading | H6: https://git-scm.com/book | I6: 5 | J6: 0 | K6: Not Started
A7: 3 | B7: 1 | D7: Foundations | E7: Git Advanced | F7: Practice rebase, cherry-pick, interactive rebase, stash; resolve 3 merge conflicts intentionally | G7: Code | H7: Pro Git ch.7 + Atlassian Git tutorial | I7: 5 | J7: 0 | K7: Not Started
A8: 4 | B8: 1 | D8: Foundations | E8: Linux CLI | F8: Master bash basics: pipes, redirection, grep, sed, awk, find, xargs; build 5 one-liners | G8: Study | H8: MIT Missing Semester lec 1-3 | I8: 5 | J8: 0 | K8: Not Started
A9: 5 | B9: 1 | D9: Foundations | E9: Python Refresh | F9: Fluent Python ch.1-3: data model, sequences, dict & set internals | G9: Reading | H9: Fluent Python — Luciano Ramalho | I9: 6 | J9: 0 | K9: Not Started
A10: 6 | B10: 1 | D10: Foundations | E10: Python Typing | F10: Master type hints, Protocol, TypedDict, Generic; convert an old script to fully typed + mypy strict clean | G10: Code | H10: mypy.readthedocs.io + PEP 484/544 | I10: 5 | J10: 0 | K10: Not Started
A11: 7 | B11: 1 | D11: Foundations | E11: CLI Project | F11: Build CLI Task Manager with Click + SQLite + pytest; push to GitHub with README + CI workflow | G11: Project | H11: github.com/pallets/click | I11: 6 | J11: 0 | K11: Not Started
A12: 8 | B12: 2 | D12: CS Fundamentals | E12: OS — Processes | F12: OSTEP ch.4-6: processes, API, scheduling; write notes + 10 flashcards | G12: Reading | H12: OSTEP (free PDF) | I12: 6 | J12: 0 | K12: Not Started
A13: 9 | B13: 2 | D13: CS Fundamentals | E13: OS — Threads | F13: OSTEP ch.26-28: threads, locks, condition variables; code a producer/consumer in Python | G13: Code | H13: OSTEP Concurrency | I13: 6 | J13: 0 | K13: Not Started
A14: 10 | B14: 2 | D14: CS Fundamentals | E14: OS — Memory | F14: Virtual memory, paging, TLB, page faults; draw memory layout diagram for a C/Python process | G14: Study | H14: OSTEP ch.13-22 | I14: 6 | J14: 0 | K14: Not Started
A15: 11 | B15: 2 | D15: CS Fundamentals | E15: Networks — TCP/IP | F15: Beej's Networking Guide; explain 3-way handshake + TCP states from memory | G15: Reading | H15: beej.us/guide/bgnet | I15: 6 | J15: 0 | K15: Not Started
A16: 12 | B16: 2 | D16: CS Fundamentals | E16: Networks — HTTP | F16: HTTP/1.1 vs HTTP/2 vs HTTP/3; inspect real traffic with curl -v and Wireshark | G16: Code | H16: MDN HTTP docs | I16: 6 | J16: 0 | K16: Not Started
... A74: 70 | B74: 10 | D74: Capstone & Interviews | E74: Behavioral Prep | F74: Prep 12 STAR stories covering leadership, conflict, failure, ambiguity, AI ethics; record yourself | G74: Interview Prep | H74: STAR method | I74: 4 | J74: 0 | K74: Not Started

Sheet Projects Tracker
A1: Projects Tracker
A2: 10 progressively harder projects — from CLI to production Multi-Agent AI SaaS
A4: # | B4: Project Name | C4: Week | D4: Level | E4: Tech Stack | F4: Difficulty | G4: Est. Hours | H4: Hours Logged | I4: Status | J4: Progress % | K4: Repo Link | L4: Demo Link | M4: Key Features | N4: Skills Gained | O4: Resume Bullet
A5: 1 | B5: Personal Finance Tracker (CLI) | C5: 1 | D5: Beginner | E5: Python · JSON | F5: 1 | G5: 5 | H5: 0 | I5: Not Started | J5: 0 | K5: github.com/yourname/cli-finance-tracker | L5: — | M5: OOP design classes (Transaction, Account), balance calculation, categories, local JSON read/write persistence, CSV export. | N5: Python classes inheritance, file system serialization, CLI menu event loop, CSV formatting. | O5: Built and shipped a command-line financial accountant tool in Python with JSON persistence and clean CSV export modules.
A6: 2 | B6: Browser History Simulator | C6: 2 | D6: Beginner | E6: Python | F6: 1 | G6: 5 | H6: 0 | I6: Not Started | J6: 0 | K6: github.com/yourname/history-simulator | L6: — | M6: LIFO browser navigation stack visit(), back(), forward() loops, history representation output logs. | N6: Stack operations push/pop, navigation pointers tracking, terminal log output formatting. | O6: Created an in-memory browser history navigation model utilizing multiple stacks in Python with undo/redo capabilities.
A7: 3 | B7: Expression AST Parser & Evaluator | C7: 3 | D7: Intermediate | E7: Python · AST | F7: 3 | G7: 5 | H7: 0 | I7: Not Started | J7: 0 | K7: github.com/yourname/ast-parser | L7: — | M7: Mathematical string parser utilizing Shunting-Yard infix to postfix conversion, AST nodes parsing, postorder traversal evaluator. | N7: Operator precedence parser mechanics, binary expression trees nodes creation, tree traversal recursive functions. | O7: Engineered a math expression parser from scratch in Python that parses strings into ASTs and evaluates them via postorder traversal.
A8: 4 | B8: Social Network Connection Router API | C8: 4 | D8: Intermediate | E8: Python · NetworkX · FastAPI | F8: 3 | G8: 6 | H8: 0 | I8: Not Started | J8: 0 | K8: github.com/yourname/social-router-api | L8: — | M8: Friends graph models using NetworkX adjacency lists, custom weighted Dijkstra paths search, mutual friends finder, FastAPI routers. | N8: Graph node/edge structures, Dijkstra shortest-path complexity optimization, REST API path params validation. | O8: Shipped a social network routing API using FastAPI and NetworkX that implements Dijkstra's algorithm to find friends pathways.
A9: 5 | B9: Task Management REST API (FastAPI + SQL) | C9: 5 | D9: Intermediate | E9: FastAPI · PostgreSQL · SQLAlchemy · Alembic | F9: 3 | G9: 8 | H9: 0 | I9: Not Started | J9: 0 | K9: github.com/yourname/fastapi-task-db-api | L9: — | M9: SQLAlchemy async models, Alembic migrations scripts, password hashing (bcrypt), JWT generation, authenticated task CRUD endpoints. | N9: Database async IO patterns, database migration loops, password encryption hashes, JWT tokens validation lifecycle. | O9: Built a secure task management REST API in FastAPI with PostgreSQL, SQLAlchemy ORM async engines, and JWT authorization checks.
A10: 6 | B10: Production Tasks Queue Service (Microservices) | C10: 6 | D10: Advanced | E10: FastAPI · Redis · Celery · Docker · Compose | F10: 4 | G10: 10 | H10: 0 | I10: Not Started | J10: 0 | K10: github.com/yourname/tasks-queue-service | L10: — | M10: Redis Cache-Aside backend query routing, custom sliding window rate limiters (Redis ZSET), Celery async workers task logs, Dockerfiles. | N10: Redis key TTL structures, sliding window logs transaction controls, Celery distributed tasks queuing, compose multi-container networks. | O10: Designed and containerized a scalable backend service incorporating Redis caching, Sliding-Window rate limiters, and Celery tasks queues.
A11: 7 | B11: Parking Lot Low-Level Design (OOD) | C11: 7 | D11: Intermediate | E11: Python · LLD · SOLID | F11: 3 | G11: 6 | H11: 0 | I11: Not Started | J11: 0 | K11: github.com/yourname/parking-lot-lld | L11: — | M11: SOLID compliant class structure mapping spot allocations, floor properties, payment gates, and ticket validation managers. | N11: Low-Level design principles, inheritance configurations, concurrency thread locks during concurrent checkout payments. | O11: Programmed a SOLID-compliant simulation of a multi-story parking lot with spot allocations logic and mock payment gates.
A12: 8 | B12: PyTorch Handwritten Digit Classifier | C12: 8 | D12: Advanced | E12: PyTorch · NumPy · Scikit-Learn | F12: 4 | G12: 6 | H12: 0 | I12: Not Started | J12: 0 | K12: github.com/yourname/mnist-pytorch-classifier | L12: — | M12: MNIST training loader pipeline, deep feedforward linear layers design, loss loops backpropagation steps, metrics precision report. | N12: Tensor manipulations, backprop mechanics, linear/nonlinear network configurations, classifier validation metrics calculation. | O12: Trained a handwritten digit classifier on PyTorch, implementing full dataset loading pipelines and metrics evaluations loops.
A13: 9 | B13: Semantic Document Q&A RAG Chatbot | C13: 9 | D13: Advanced | E13: FastAPI · ChromaDB · OpenAI API · Pytest | F13: 4 | G13: 8 | H13: 0 | I13: Not Started | J13: 0 | K13: github.com/yourname/rag-doc-chatbot | L13: — | M13: PDF text extraction, semantic paragraph splitting pipelines, ChromaDB vector store collection seeding, prompt injections. | N13: Vector databases index queries, semantic chunking strategy tradeoffs, OpenAI embeddings calls, integration testing (Pytest). | O13: Architected a Q&A chatbot using semantic RAG, integrating ChromaDB, OpenAI APIs, and validation modules verified via Pytest.
A14: 10 | B14: Flagship AI Research Assistant (Multi-Agent) | C14: 10 | D14: Capstone | E14: FastAPI · LangGraph · ChromaDB · React · Tavily API | F14: 5 | G14: 20 | H14: 0 | I14: Not Started | J14: 0 | K14: github.com/yourname/langgraph-research-agent | L14: https://research-assistant.demo.com | M14: LangGraph state machine supervisor nodes routing, Tavily web search tools integrations, server-sent events stream, React UI. | N14: Multi-agent loop states structures, streaming server-sent streams, React stream chunks parser, multi-container compose deploys. | O14: Launched a flagship multi-agent research portal utilizing LangGraph state control, stream parsing interfaces, and Tavily search tools.

Sheet Milestones
A1: Milestones
A2: 20 checkpoints that prove real progress — 2 per week
A4: # | B4: Week | C4: Milestone | D4: Description | E4: Acceptance Criteria | F4: Target Date | G4: Achieved Date | H4: Status | I4: Reward
A5: 1 | B5: 1 | C5: Dev Environment Ready | D5: Fully configured local dev environment with linting and formatting on save | E5: VS Code, Python 3.11, ruff, black, mypy installed; dotfiles repo public | H5: Not Started | I5: New keyboard shortcut sticker on laptop ⌨️
A6: 2 | B6: 1 | C6: First Public CLI Shipped | D6: CLI Task Manager live on GitHub with CI passing | E6: Repo has README, MIT license, GH Actions green, >=80% test coverage | H6: Not Started | I6: Tweet the repo link 🐦
A7: 3 | B7: 2 | C7: CS Fundamentals Notes | D7: Complete OS + Networks + DBMS notes in knowledge base | E7: >=30 pages markdown, with diagrams and 50 flashcards | H7: Not Started | I7: Favorite coffee outing ☕
A8: 4 | B8: 2 | C8: First 50 Flashcards | D8: Seed your spaced-repetition system | E8: 50 cards in Anki/Mochi/own tracker, all reviewed once | H8: Not Started | I8: 1 movie night 🎬
A9: 5 | B9: 3 | C9: SOLID Refactor | D9: Refactor TODO API to layered architecture | E9: Repository pattern, services layer, 90%+ tests, no SRP violations | H9: Not Started | I9: Buy that programming book you wanted 📚
A10: 6 | B10: 3 | C10: First 100 LeetCode Easy/Medium | D10: Build problem-solving fluency | E10: 100 problems solved on LeetCode, all neetcode.io easy patterns done | H10: Not Started | I10: Sunday off, no laptop 🌳
A11: 7 | B11: 4 | C11: Production REST API Live | D11: Ship the Week 4 deliverable | E11: API deployed locally with auth, migrations, OpenAPI; 25+ endpoints | H11: Not Started | I11: Treat yourself to a nice dinner 🍣
A12: 8 | B12: 4 | C12: Auth Mastery Checkpoint | D12: Explain JWT auth flow from memory on whiteboard | E12: 5-min recorded explanation covering access/refresh/rotation/blacklist | H12: Not Started | I12: Share the recording on LinkedIn 💼
A13: 9 | B13: 5 | C13: First Container in Production | D13: Deploy first Docker container to AWS EC2 | E13: Live URL serving HTTPS traffic through Nginx | H13: Not Started | I13: New mechanical keyboard? 😎
A14: 10 | B14: 5 | C14: CI/CD Pipeline Green | D14: Automated build/test/deploy pipeline | E14: Push to main → live in <5 min; rollback documented | H14: Not Started | I14: Weekend hike 🥾
A15: 11 | B15: 6 | C15: Neural Net from Scratch | D15: Build & train MLP without frameworks | E15: micrograd-style implementation; trains on MNIST to >=95% | H15: Not Started | I15: Frame the loss curve 📈
A16: 12 | B16: 6 | C16: Sentiment API Deployed | D16: HuggingFace model live in production | E16: Public endpoint with Swagger; >=85% accuracy on IMDb test | H16: Not Started | I16: Order a fun gadget 🎁
... A24: 20 | B24: 10 | C24: FAANG-Ready | D24: Resume sent + 5 mock interviews done | E24: Resume reviewed; 5 mocks >=75% avg; 12 STAR stories memorized | H24: Not Started | I24: Apply to 10 target roles 🎯

Sheet Interview Prep
A1: Interview Prep Questions
A2: 60+ core questions across Python, SQL, DSA, OOD, OS, DBMS, System Design, AI, and Behavioral
A4: Topic | B4: Interview Question | C4: Difficulty | D4: Target Companies | E4: Status | F4: Notes
A5: Python | B5: Explain the GIL and its impact on multithreading vs multiprocessing | C5: Medium | D5: Google, Meta | E5: Not Started
A6: Python | B6: What's the difference between __new__ and __init__? When would you override __new__? | C6: Medium | D6: Meta, Amazon | E6: Not Started
A7: Python | B7: Explain how Python's MRO works with multiple inheritance (C3 linearization) | C7: Hard | D7: Google, Stripe | E7: Not Started
A8: Python | B8: How does Python's garbage collector handle reference cycles? | C8: Hard | D8: Meta, Microsoft | E8: Not Started
A9: Python | B9: Implement a decorator that retries a function with exponential backoff | C9: Medium | D9: OpenAI, Anthropic | E9: Not Started
A10: Python | B10: What are metaclasses in Python and how do they modify class generation? | C10: Hard | D10: Google, Netflix | E10: Not Started
A11: Python | B11: Explain the difference between deepcopy and shallow copy in nested data structures | C11: Easy | D11: Apple, Microsoft | E11: Not Started
A12: Python | B12: How do generators work under the hood and what is the function of the yield statement? | C12: Medium | D12: Amazon, Uber | E12: Not Started
A13: SQL | B13: Write a query to find the second-highest salary per department | C13: Medium | D13: Amazon, Google | E13: Not Started
A14: SQL | B14: Explain B-tree vs hash indexes; when would you use each? | C14: Medium | D14: Meta, Stripe | E14: Not Started
A15: SQL | B15: What is a covering index? Show an EXPLAIN that benefits from one | C15: Hard | D15: Google, Snowflake | E15: Not Started
A16: SQL | B16: Difference between WHERE and HAVING? Can HAVING work without GROUP BY? | C16: Easy | D16: Amazon | E16: Not Started
... A59: Behavioral | B59: Why are you looking to become an AI Software Engineer specifically, and what drives you in this field? | C59: Easy | D59: All Tech | E59: Not Started

Sheet LeetCode Tracker
A1: LeetCode Problems Tracker
A2: 130+ LeetCode problems aligned week-by-week with your curriculum patterns
A4: Week # | B4: Problem # | C4: Problem Title | D4: Difficulty | E4: Pattern / Category | F4: URL | G4: Status | H4: Date Solved | I4: Notes
A5: 1 | B5: 1 | C5: Two Sum | D5: Easy | E5: Arrays & Hash Map | F5: https://leetcode.com/problems/two-sum/ | G5: Not Started
A6: 1 | B6: 9 | C6: Palindrome Number | D6: Easy | E6: Math | F6: https://leetcode.com/problems/palindrome-number/ | G6: Not Started
A7: 1 | B7: 13 | C7: Roman to Integer | D7: Easy | E7: Strings & Hash Map | F7: https://leetcode.com/problems/roman-to-integer/ | G7: Not Started
A8: 1 | B8: 14 | C8: Longest Common Prefix | D8: Easy | E8: Strings | F8: https://leetcode.com/problems/longest-common-prefix/ | G8: Not Started
A9: 1 | B9: 20 | C9: Valid Parentheses | D9: Easy | E9: Stack & Strings | F9: https://leetcode.com/problems/valid-parentheses/ | G9: Not Started
A10: 1 | B10: 66 | C10: Plus One | D10: Easy | E10: Arrays & Math | F10: https://leetcode.com/problems/plus-one/ | G10: Not Started
A11: 1 | B11: 67 | C11: Add Binary | D11: Easy | E11: Strings & Math | F11: https://leetcode.com/problems/add-binary/ | G11: Not Started
A12: 1 | B12: 83 | C12: Remove Duplicates from Sorted List | D12: Easy | E12: Linked List | F12: https://leetcode.com/problems/remove-duplicates-from-sorted-list/ | G12: Not Started
A13: 1 | B13: 88 | C13: Merge Sorted Array | D13: Easy | E13: Arrays & Two Pointers | F13: https://leetcode.com/problems/merge-sorted-array/ | G13: Not Started
A14: 1 | B14: 118 | C14: Pascal's Triangle | D14: Easy | E14: Arrays & DP | F14: https://leetcode.com/problems/pascals-triangle/ | G14: Not Started
A15: 2 | B15: 121 | C15: Best Time to Buy and Sell Stock | D15: Easy | E15: Arrays & Sliding Window | F15: https://leetcode.com/problems/best-time-to-buy-and-sell-stock/ | G15: Not Started
A16: 2 | B16: 125 | C16: Valid Palindrome | D16: Easy | E16: Strings & Two Pointers | F16: https://leetcode.com/problems/valid-palindrome/ | G16: Not Started
... A166: 7 | B166: 185 | C166: Department Top Three Salaries | D166: Hard | E166: SQL | F166: https://leetcode.com/problems/department-top-three-salaries/ | G166: Not Started

Sheet Resources Library
A1: Ranked Resources Library
A2: Top-tier reference books, official documentation, courses, and playlists
A4: Week # | B4: Resource Name | C4: Type | D4: Reference Link / URL | E4: Status | F4: Notes
A5: 1 | B5: Python Official Tutorial | C5: Docs | D5: https://docs.python.org/3/tutorial | E5: Not Started | F5: Standard syntax guides, statements, and module systems.
A6: 1 | B6: Corey Schafer Python (Videos 1-20) | C6: YouTube | D6: https://youtube.com/c/CoreySchafer | E6: Not Started | F6: Essential Python configurations, scope rules, and library modules.
A7: 1 | B7: Fluent Python (Luciano Ramalho) | C7: Book | D7: https://www.oreilly.com/library/view/fluent-python-2nd/9781492056348/ | E7: Not Started | F7: Pythonic protocols, data structures, and classes design models.
A8: 1 | B8: Pro Git (Scott Chacon & Ben Straub) | C8: Book | D8: https://git-scm.com/book | E8: Not Started | F8: Advanced branching model, local configurations, and internal mechanisms.
A9: 2 | B9: OS: Three Easy Pieces (Arpaci-Dusseau) | C9: Book | D9: https://ostep.org | E9: Not Started | F9: Process cycles, threading synchronization locks, and CPU schedulers.
A10: 2 | B10: MIT Missing Semester (Lecture 1-3) | C10: Course | D10: https://missing.csail.mit.edu | E10: Not Started | F10: Bash scripting, pipeline structures, and tools configs.
A11: 2 | B11: Beej's Guide to Network Programming | C11: Docs | D11: https://beej.us/guide/bgnet | E11: Not Started | F11: Sockets bindings, connections handling, and TCP packets structures.
A12: 3 | B12: Refactoring.Guru Design Patterns | C12: Docs | D12: https://refactoring.guru | E12: Not Started | F12: Design pattern definitions, Python code examples, and UML representations.
A13: 3 | B13: Clean Code (Robert C. Martin) | C13: Book | D13: https://www.oreilly.com/library/view/clean-code-a/9780136083238/ | E13: Not Started | F13: SOLID properties, functions design, and names formatting rules.
A14: 4 | B14: FastAPI Official Tutorial | C14: Docs | D14: https://fastapi.tiangolo.com | E14: Not Started | F14: Routing schemas, dependency injection models, and middleware controllers.
A15: 4 | B15: SQLAlchemy 2.0 Documentation | C15: Docs | D15: https://docs.sqlalchemy.org | E15: Not Started | F15: Declarative mappings, transaction contexts, and asynchronous databases engine calls.
A16: 5 | B16: Docker Deep Dive (Nigel Poulton) | C16: Book | D16: https://dockerdeepdive.com | E16: Not Started | F16: Image layer optimizations, compose loops configurations, and docker networks.
... A26: 10 | B26: NeetCode System Design Course | C26: Course | D26: https://neetcode.io | E26: Not Started | F26: Architectural walk-throughs, scale evaluations, and interviewer mock logs.

Sheet Weekly Metrics
A1: Weekly Metrics Log
A2: Track targets vs. actual progress, revise weak topics weekly
A4: Week # | B4: Study Hours (Target) | C4: Study Hours (Actual) | D4: LeetCode Problems (Target) | E4: LeetCode Problems (Actual) | F4: Mock Interview Completed | G4: Weak Areas Identified | H4: Corrective Actions
A5: 1 | B5: 50 | C5: ='Weekly Goals'!H5 | D5: 15 | E5: =COUNTIFS('LeetCode Tracker'!A:A,1,'LeetCode Tracker'!G:G,"Complete") | F5: No
A6: 2 | B6: 50 | C6: ='Weekly Goals'!H6 | D6: 15 | E6: =COUNTIFS('LeetCode Tracker'!A:A,2,'LeetCode Tracker'!G:G,"Complete") | F6: No
A7: 3 | B7: 50 | C7: ='Weekly Goals'!H7 | D7: 15 | E7: =COUNTIFS('LeetCode Tracker'!A:A,3,'LeetCode Tracker'!G:G,"Complete") | F7: No
A8: 4 | B8: 50 | C8: ='Weekly Goals'!H8 | D8: 15 | E8: =COUNTIFS('LeetCode Tracker'!A:A,4,'LeetCode Tracker'!G:G,"Complete") | F8: No
A9: 5 | B9: 50 | C9: ='Weekly Goals'!H9 | D9: 15 | E9: =COUNTIFS('LeetCode Tracker'!A:A,5,'LeetCode Tracker'!G:G,"Complete") | F9: No
A10: 6 | B10: 50 | C10: ='Weekly Goals'!H10 | D10: 15 | E10: =COUNTIFS('LeetCode Tracker'!A:A,6,'LeetCode Tracker'!G:G,"Complete") | F10: No
A11: 7 | B11: 50 | C11: ='Weekly Goals'!H11 | D11: 15 | E11: =COUNTIFS('LeetCode Tracker'!A:A,7,'LeetCode Tracker'!G:G,"Complete") | F11: No
A12: 8 | B12: 50 | C12: ='Weekly Goals'!H12 | D12: 15 | E12: =COUNTIFS('LeetCode Tracker'!A:A,8,'LeetCode Tracker'!G:G,"Complete") | F12: No
A13: 9 | B13: 50 | C13: ='Weekly Goals'!H13 | D13: 15 | E13: =COUNTIFS('LeetCode Tracker'!A:A,9,'LeetCode Tracker'!G:G,"Complete") | F13: No
A14: 10 | B14: 50 | C14: ='Weekly Goals'!H14 | D14: 15 | E14: =COUNTIFS('LeetCode Tracker'!A:A,10,'LeetCode Tracker'!G:G,"Complete") | F14: No

Sheet Notes & Journal
A1: Conceptual Notes & Daily Journal
A2: Log custom study notes, code snippets, blockages, and daily reflections
A4: Date | B4: Week # | C4: Day # | D4: Focus Area | E4: Key Takeaways / Concept Breakdown | F4: Code Snippets | G4: Blockers / Questions | H4: Next Steps
B5: 1 | C5: 1
B6: 1 | C6: 2
B7: 1 | C7: 3
B8: 1 | C8: 4
B9: 1 | C9: 5
B10: 1 | C10: 6
B11: 1 | C11: 7
B12: 2 | C12: 8
B13: 2 | C13: 9
B14: 2 | C14: 10
B15: 2 | C15: 11
B16: 2 | C16: 12
... B74: 10 | C74: 70
